datacontainerqnp/__init__.py
datacontainerqnp/_pandas_stock_adapter.py
datacontainerqnp/_pandas_stock_sync_rest_client.py
datacontainerqnp/_polygon_rest_utils.py
datacontainerqnp/_polygon_sync_rest_client.py
datacontainerqnp/constants.py
datacontainerqnp/types.py
datacontainerqnp-0.1.0.dist-info/METADATA
datacontainerqnp-0.1.0.dist-info/WHEEL
datacontainerqnp-0.1.0.dist-info/top_level.txt
datacontainerqnp-0.1.0.dist-info/RECORD
