Metadata-Version: 2.1
Name: datacontainerqnp
Version: 0.1.0
Summary: UNKNOWN
Home-page: UNKNOWN
License: UNKNOWN
Platform: UNKNOWN
Requires-Dist: stockutilitiesqnp
Requires-Dist: pandas
Requires-Dist: requests
